{
  "meta": {
    "weights_baseline": "C:\\Arib\\MASSA AYAM\\generalisasi-ayam-skripsi\\train model\\runs_compare\\cmp_yolov8m\\weights\\best.pt",
    "weights_ft": "C:\\Arib\\MASSA AYAM\\generalisasi-ayam-skripsi\\train model\\runs_rectified\\ft_rectified_yolov8m\\weights\\best.pt",
    "imgsz": 960,
    "device": "0",
    "primary_metric": "map50_95",
    "neutral_eps": 0.005,
    "datasets": [
      {
        "id": "pio_val",
        "display": "PIO val (in-domain)",
        "in_domain": true
      },
      {
        "id": "broiler_instance_seg",
        "display": "Roboflow broiler_instance_seg (external)",
        "in_domain": false
      },
      {
        "id": "chicken_detection_fum",
        "display": "Roboflow chicken_detection_fum (external)",
        "in_domain": false
      }
    ]
  },
  "variants": [
    {
      "name": "baseline",
      "status": "ok",
      "source": "eval",
      "note": "Bobot baseline, gambar asli (referensi Δ).",
      "weights": "C:\\Arib\\MASSA AYAM\\generalisasi-ayam-skripsi\\train model\\runs_compare\\cmp_yolov8m\\weights\\best.pt",
      "rectified_root": null,
      "datasets": {
        "pio_val": {
          "status": "ok",
          "images": 452,
          "map50": 0.8997,
          "map50_95": 0.71024,
          "precision": 0.95845,
          "recall": 0.88788
        },
        "broiler_instance_seg": {
          "status": "ok",
          "images": 200,
          "map50": 0.81072,
          "map50_95": 0.53553,
          "precision": 0.8193,
          "recall": 0.76952
        },
        "chicken_detection_fum": {
          "status": "ok",
          "images": 326,
          "map50": 0.13375,
          "map50_95": 0.05823,
          "precision": 0.56592,
          "recall": 0.144
        }
      },
      "verdict": {
        "overall": "baseline",
        "mean_delta_primary": 0.0,
        "per_dataset": [
          {
            "dataset": "pio_val",
            "delta": 0.0,
            "label": "baseline"
          },
          {
            "dataset": "broiler_instance_seg",
            "delta": 0.0,
            "label": "baseline"
          },
          {
            "dataset": "chicken_detection_fum",
            "delta": 0.0,
            "label": "baseline"
          }
        ],
        "n_better": 0,
        "n_worse": 0,
        "n_neutral": 0
      }
    },
    {
      "name": "mowa_1pass",
      "status": "ok",
      "source": "eval",
      "note": "MOWA 1 pass, bobot baseline.",
      "weights": "C:\\Arib\\MASSA AYAM\\generalisasi-ayam-skripsi\\train model\\runs_compare\\cmp_yolov8m\\weights\\best.pt",
      "rectified_root": "C:\\Arib\\MASSA AYAM\\generalisasi-ayam-skripsi\\data\\rectified",
      "datasets": {
        "pio_val": {
          "status": "ok",
          "images": 452,
          "map50": 0.89734,
          "map50_95": 0.6383,
          "precision": 0.96001,
          "recall": 0.87802
        },
        "broiler_instance_seg": {
          "status": "ok",
          "images": 200,
          "map50": 0.77769,
          "map50_95": 0.45645,
          "precision": 0.79172,
          "recall": 0.74709
        },
        "chicken_detection_fum": {
          "status": "ok",
          "images": 326,
          "map50": 0.1253,
          "map50_95": 0.0491,
          "precision": 0.49998,
          "recall": 0.14092
        }
      },
      "verdict": {
        "per_dataset": [
          {
            "dataset": "pio_val",
            "delta": -0.07194,
            "label": "worse"
          },
          {
            "dataset": "broiler_instance_seg",
            "delta": -0.07908,
            "label": "worse"
          },
          {
            "dataset": "chicken_detection_fum",
            "delta": -0.00913,
            "label": "worse"
          }
        ],
        "mean_delta_primary": -0.05338,
        "overall": "worse",
        "n_better": 0,
        "n_worse": 3,
        "n_neutral": 0
      }
    },
    {
      "name": "mowa_1pass_ft",
      "status": "ok",
      "source": "eval",
      "note": "MOWA 1 pass, bobot fine-tune-on-rectified (rectify-both).",
      "weights": "C:\\Arib\\MASSA AYAM\\generalisasi-ayam-skripsi\\train model\\runs_rectified\\ft_rectified_yolov8m\\weights\\best.pt",
      "rectified_root": "C:\\Arib\\MASSA AYAM\\generalisasi-ayam-skripsi\\data\\rectified",
      "datasets": {
        "pio_val": {
          "status": "ok",
          "images": 452,
          "map50": 0.90817,
          "map50_95": 0.68332,
          "precision": 0.96367,
          "recall": 0.89086
        },
        "broiler_instance_seg": {
          "status": "ok",
          "images": 200,
          "map50": 0.85578,
          "map50_95": 0.52984,
          "precision": 0.8805,
          "recall": 0.83261
        },
        "chicken_detection_fum": {
          "status": "ok",
          "images": 326,
          "map50": 0.13493,
          "map50_95": 0.05823,
          "precision": 0.50945,
          "recall": 0.1496
        }
      },
      "verdict": {
        "per_dataset": [
          {
            "dataset": "pio_val",
            "delta": -0.02692,
            "label": "worse"
          },
          {
            "dataset": "broiler_instance_seg",
            "delta": -0.00569,
            "label": "worse"
          },
          {
            "dataset": "chicken_detection_fum",
            "delta": 0.0,
            "label": "neutral"
          }
        ],
        "mean_delta_primary": -0.01087,
        "overall": "worse",
        "n_better": 0,
        "n_worse": 2,
        "n_neutral": 1
      }
    },
    {
      "name": "mowa_coarse",
      "status": "ok",
      "source": "eval",
      "note": "MOWA coarse-only (TPS, buang residual flow), bobot baseline.",
      "weights": "C:\\Arib\\MASSA AYAM\\generalisasi-ayam-skripsi\\train model\\runs_compare\\cmp_yolov8m\\weights\\best.pt",
      "rectified_root": "C:\\Arib\\MASSA AYAM\\generalisasi-ayam-skripsi\\data\\rectified_coarse",
      "datasets": {
        "pio_val": {
          "status": "ok",
          "images": 452,
          "map50": 0.89631,
          "map50_95": 0.63537,
          "precision": 0.96021,
          "recall": 0.87529
        },
        "broiler_instance_seg": {
          "status": "ok",
          "images": 200,
          "map50": 0.78442,
          "map50_95": 0.46699,
          "precision": 0.79629,
          "recall": 0.76105
        },
        "chicken_detection_fum": {
          "status": "ok",
          "images": 326,
          "map50": 0.12313,
          "map50_95": 0.04898,
          "precision": 0.52241,
          "recall": 0.13795
        }
      },
      "verdict": {
        "per_dataset": [
          {
            "dataset": "pio_val",
            "delta": -0.07487,
            "label": "worse"
          },
          {
            "dataset": "broiler_instance_seg",
            "delta": -0.06854,
            "label": "worse"
          },
          {
            "dataset": "chicken_detection_fum",
            "delta": -0.00925,
            "label": "worse"
          }
        ],
        "mean_delta_primary": -0.05089,
        "overall": "worse",
        "n_better": 0,
        "n_worse": 3,
        "n_neutral": 0
      }
    },
    {
      "name": "mowa_alpha05",
      "status": "ok",
      "source": "eval",
      "note": "MOWA warp-alpha=0.5 (perlemah warp), bobot baseline.",
      "weights": "C:\\Arib\\MASSA AYAM\\generalisasi-ayam-skripsi\\train model\\runs_compare\\cmp_yolov8m\\weights\\best.pt",
      "rectified_root": "C:\\Arib\\MASSA AYAM\\generalisasi-ayam-skripsi\\data\\rectified_alpha05",
      "datasets": {
        "pio_val": {
          "status": "ok",
          "images": 452,
          "map50": 0.88921,
          "map50_95": 0.66002,
          "precision": 0.96065,
          "recall": 0.8767
        },
        "broiler_instance_seg": {
          "status": "ok",
          "images": 200,
          "map50": 0.79163,
          "map50_95": 0.47331,
          "precision": 0.78914,
          "recall": 0.7657
        },
        "chicken_detection_fum": {
          "status": "ok",
          "images": 326,
          "map50": 0.13047,
          "map50_95": 0.0534,
          "precision": 0.51467,
          "recall": 0.14555
        }
      },
      "verdict": {
        "per_dataset": [
          {
            "dataset": "pio_val",
            "delta": -0.05022,
            "label": "worse"
          },
          {
            "dataset": "broiler_instance_seg",
            "delta": -0.06222,
            "label": "worse"
          },
          {
            "dataset": "chicken_detection_fum",
            "delta": -0.00483,
            "label": "neutral"
          }
        ],
        "mean_delta_primary": -0.03909,
        "overall": "worse",
        "n_better": 0,
        "n_worse": 2,
        "n_neutral": 1
      }
    },
    {
      "name": "mowa_pad015",
      "status": "ok",
      "source": "eval",
      "note": "MOWA pad-frac=0.15 (jaga tepi, box tak dibuang), bobot baseline.",
      "weights": "C:\\Arib\\MASSA AYAM\\generalisasi-ayam-skripsi\\train model\\runs_compare\\cmp_yolov8m\\weights\\best.pt",
      "rectified_root": "C:\\Arib\\MASSA AYAM\\generalisasi-ayam-skripsi\\data\\rectified_pad015",
      "datasets": {
        "pio_val": {
          "status": "ok",
          "images": 452,
          "map50": 0.88759,
          "map50_95": 0.61464,
          "precision": 0.95274,
          "recall": 0.87541
        },
        "broiler_instance_seg": {
          "status": "ok",
          "images": 200,
          "map50": 0.88412,
          "map50_95": 0.59606,
          "precision": 0.92633,
          "recall": 0.85338
        },
        "chicken_detection_fum": {
          "status": "ok",
          "images": 326,
          "map50": 0.12654,
          "map50_95": 0.04958,
          "precision": 0.51366,
          "recall": 0.14174
        }
      },
      "verdict": {
        "per_dataset": [
          {
            "dataset": "pio_val",
            "delta": -0.0956,
            "label": "worse"
          },
          {
            "dataset": "broiler_instance_seg",
            "delta": 0.06053,
            "label": "better"
          },
          {
            "dataset": "chicken_detection_fum",
            "delta": -0.00865,
            "label": "worse"
          }
        ],
        "mean_delta_primary": -0.01457,
        "overall": "worse",
        "n_better": 1,
        "n_worse": 2,
        "n_neutral": 0
      }
    },
    {
      "name": "mowa_coarse_sam",
      "status": "ok",
      "source": "eval",
      "note": "MOWA coarse-only + label bbox via mask SAM (Lever B), bobot baseline.",
      "weights": "C:\\Arib\\MASSA AYAM\\generalisasi-ayam-skripsi\\train model\\runs_compare\\cmp_yolov8m\\weights\\best.pt",
      "rectified_root": "C:\\Arib\\MASSA AYAM\\generalisasi-ayam-skripsi\\data\\rectified_coarse_sam",
      "datasets": {
        "pio_val": {
          "status": "ok",
          "images": 452,
          "map50": 0.89827,
          "map50_95": 0.55453,
          "precision": 0.95946,
          "recall": 0.88124
        },
        "broiler_instance_seg": {
          "status": "ok",
          "images": 200,
          "map50": 0.79265,
          "map50_95": 0.49495,
          "precision": 0.81114,
          "recall": 0.75343
        },
        "chicken_detection_fum": {
          "status": "ok",
          "images": 326,
          "map50": 0.14201,
          "map50_95": 0.08342,
          "precision": 0.52558,
          "recall": 0.15759
        }
      },
      "verdict": {
        "per_dataset": [
          {
            "dataset": "pio_val",
            "delta": -0.15571,
            "label": "worse"
          },
          {
            "dataset": "broiler_instance_seg",
            "delta": -0.04058,
            "label": "worse"
          },
          {
            "dataset": "chicken_detection_fum",
            "delta": 0.02519,
            "label": "better"
          }
        ],
        "mean_delta_primary": -0.05703,
        "overall": "worse",
        "n_better": 1,
        "n_worse": 2,
        "n_neutral": 0
      }
    }
  ]
}